mcp_build_toolchain/__init__.py
mcp_build_toolchain/server.py
mcp_build_toolchain-0.1.1.dist-info/METADATA
mcp_build_toolchain-0.1.1.dist-info/WHEEL
mcp_build_toolchain-0.1.1.dist-info/entry_points.txt
mcp_build_toolchain-0.1.1.dist-info/RECORD
