Metadata-Version: 2.4
Name: mcp-build-toolchain
Version: 0.1.1
Summary: MCP server that help to build and fix compilation errors
Project-URL: Homepage, https://github.com/jlopezm/mcp_build_toolchain
Author: Joaquin Lopez
Requires-Python: >=3.10
Requires-Dist: mcp>=1.3.0
